wson/__init__.py
wson/wson.py
wson-0.2.4.dist-info/LICENSE
wson-0.2.4.dist-info/METADATA
wson-0.2.4.dist-info/WHEEL
wson-0.2.4.dist-info/RECORD
