Metadata-Version: 2.1
Name: wson
Version: 0.2.4
Summary: WSON (Web Simple Object Notation)
Home-page: https://github.com/lunastev/wson
License: MIT
Author: LunaStev
Author-email: lunastev@gurmstudios.com
Requires-Python: >=3.5,<4.0
Classifier: License :: OSI Approved :: MIT License
Classifier: Programming Language :: Python :: 3
Classifier: Programming Language :: Python :: 3.5
Classifier: Programming Language :: Python :: 3.6
Classifier: Programming Language :: Python :: 3.7
Classifier: Programming Language :: Python :: 3.8
Classifier: Programming Language :: Python :: 3.9
Classifier: Programming Language :: Python :: 3.10
Classifier: Programming Language :: Python :: 3.11
Classifier: Programming Language :: Python :: 3.12
Project-URL: Repository, https://github.com/lunastev/wson
